bytecrypt/__init__.py
bytecrypt/__main__.py
bytecrypt/bytecrypt.py
bytecrypt-0.3.1.dist-info/LICENSE
bytecrypt-0.3.1.dist-info/METADATA
bytecrypt-0.3.1.dist-info/WHEEL
bytecrypt-0.3.1.dist-info/top_level.txt
bytecrypt-0.3.1.dist-info/RECORD
