Metadata-Version: 2.1
Name: bytecrypt
Version: 0.3.1
Summary: Easily encrypt/decrypt data with password
License: MIT License
Keywords: encrypt,decrypt,bytecrypt,encryption,decryption
Classifier: License :: OSI Approved :: MIT License
Classifier: Programming Language :: Python
Classifier: Programming Language :: Python :: 3
Requires-Python: >=3.9
License-File: LICENSE
Requires-Dist: cryptography
